django_registration_invite-0.0.3.dist-info/DESCRIPTION.rst
django_registration_invite-0.0.3.dist-info/METADATA
django_registration_invite-0.0.3.dist-info/RECORD
django_registration_invite-0.0.3.dist-info/WHEEL
django_registration_invite-0.0.3.dist-info/metadata.json
django_registration_invite-0.0.3.dist-info/top_level.txt
registration_invite/__init__.py
registration_invite/admin.py
registration_invite/forms.py
registration_invite/models.py
registration_invite/views.py
registration_invite/templates/admin/invitation_button.html
registration_invite/templates/admin/registration_invitation.html
registration_invite/templates/admin/auth/app_index.html
registration_invite/templates/admin/auth/change_list.html
registration_invite/templates/registration/invite/activation_complete.html
registration_invite/templates/registration/invite/activation_form.html
registration_invite/templates/registration/invite/invitation_complete.html
registration_invite/templates/registration/invite/invitation_form.html
registration_invite/templates/registration/invite/email/body.txt
registration_invite/templates/registration/invite/email/subject.txt
registration_invite/urls/__init__.py
registration_invite/urls/activation.py
registration_invite/urls/invitation.py
